{
  "questions": [
    {
      "question": "AI生成コードで最も見つかりやすいバグの種類はどれですか？",
      "options": [
        "コンパイルエラー",
        "境界値の誤り（>= と > の間違いなど）",
        "変数名のスペルミス",
        "インポートの不足"
      ],
      "answer": 1,
      "explanation": "AIは構文的に正しいコードを生成しますが、>=と>の違いなど、境界値のロジックを微妙に間違えることがよくあります。型エラーやコンパイルエラーは少ないです。"
    },
    {
      "question": "AI生成コードをレビューするとき、最初にすべきことはどれですか？",
      "options": [
        "すぐにテストを書き始める",
        "コードを読む前に要件を理解する",
        "AIに修正を依頼する",
        "パフォーマンスを測定する"
      ],
      "answer": 1,
      "explanation": "まず要件を理解してから、コードが要件通りに実装されているかを確認します。要件を理解せずにコードを読んでも、バグを見つけることは困難です。"
    },
    {
      "question": "重複チェックで「部分的な重なり」を検出するために必要な条件はどれですか？",
      "options": [
        "開始時間が完全に一致する場合のみチェック",
        "終了時間が完全に一致する場合のみチェック",
        "新しい予約の開始 < 既存の終了 かつ 新しい予約の終了 > 既存の開始",
        "新しい予約が既存の予約と完全に同じ時間帯の場合のみチェック"
      ],
      "answer": 2,
      "explanation": "時間帯の重なりを検出するには「新しい予約の開始が既存の終了より前」かつ「新しい予約の終了が既存の開始より後」を確認します。完全一致だけでは部分的な重なりを見逃します。"
    }
  ]
}
